ConcurrentImageRead/ConcurrentImageRead.py
ConcurrentImageRead/__init__.py
ConcurrentImageRead/core.py
ConcurrentImageRead-0.0.10.dist-info/LICENSE
ConcurrentImageRead-0.0.10.dist-info/METADATA
ConcurrentImageRead-0.0.10.dist-info/WHEEL
ConcurrentImageRead-0.0.10.dist-info/top_level.txt
ConcurrentImageRead-0.0.10.dist-info/RECORD
