Metadata-Version: 2.1
Name: ConcurrentImageRead
Version: 0.0.10
Summary: Read Image Directory or Image List simultaneously with multi-processing
Home-page: https://github.com/adityamangal1998/Concurrent-Image-Read.git
Author: Aditya Mangal
Author-email: adityamangal98@gmail.com
License: MIT
Classifier: License :: OSI Approved :: MIT License
Classifier: Programming Language :: Python :: 3
Classifier: Programming Language :: Python :: 3.7
License-File: LICENSE
Requires-Dist: opencv-python (>=4.5)
Requires-Dist: numpy (>=1.17)
Requires-Dist: future (>=0.17)
Requires-Dist: glob2 (>=0.7)
